onegeo_chat_client/__init__.py
onegeo_chat_client-2.1.3.dist-info/METADATA
onegeo_chat_client-2.1.3.dist-info/WHEEL
onegeo_chat_client-2.1.3.dist-info/top_level.txt
onegeo_chat_client-2.1.3.dist-info/RECORD
