Metadata-Version: 2.4
Name: onegeo-chat-client
Version: 2.1.3
Summary: RAG based chatbot client
Author-email: Mathilde POMMIER <mpommier@neogeo.fr>, Sébastien DA ROCHA <sdarocha@neogeo.fr>
Requires-Python: >=3.10
Requires-Dist: requests
